indiagrid/__init__.py
indiagrid/module.py
indiagrid-0.4.1.dist-info/LICENSE
indiagrid-0.4.1.dist-info/METADATA
indiagrid-0.4.1.dist-info/WHEEL
indiagrid-0.4.1.dist-info/top_level.txt
indiagrid-0.4.1.dist-info/RECORD
