Metadata-Version: 2.2
Name: indiagrid
Version: 0.4.1
Summary: A library for WGS84 to Indian Grid System conversion.
Home-page: https://github.com/goki75/indiagrid
Author: G Kiran
Author-email: G Kiran <goki75@gmail.com>
License: GNU Lesser General Public License v2.1
Project-URL: homepage, https://github.com/goki75/indiagrid
Project-URL: repository, https://github.com/goki75/indiagrid
Keywords: location,geography,encoding,decoding,latitude,longitude
Classifier: Programming Language :: Python :: 3
Classifier: License :: OSI Approved :: MIT License
Classifier: Intended Audience :: Developers
Classifier: Topic :: Software Development :: Libraries :: Python Modules
Requires-Python: >=3.1
License-File: LICENSE
Dynamic: author
Dynamic: home-page
Dynamic: requires-python
